meteoalarm_rssapi/__init__.py
meteoalarm_rssapi/_client.py
meteoalarm_rssapi/_helpers.py
meteoalarm_rssapi/_parser.py
meteoalarm_rssapi/_resources.py
meteoalarm_rssapi/_webquery.py
meteoalarm_rssapi/exceptions.py
meteoalarm_rssapi-1.0.5.dist-info/LICENSE.txt
meteoalarm_rssapi-1.0.5.dist-info/METADATA
meteoalarm_rssapi-1.0.5.dist-info/WHEEL
meteoalarm_rssapi-1.0.5.dist-info/top_level.txt
meteoalarm_rssapi-1.0.5.dist-info/RECORD
