Metadata-Version: 2.1
Name: meteoalarm-rssapi
Version: 1.0.5
Summary: An "API" for meteoalarm.eu using the rss feeds.
Home-page: https://github.com/xlcnd/meteoalarm-rssapi
Author: xlcnd
Author-email: xlcnd@outlook.com
License: GPL v3
Download-URL: https://github.com/xlcnd/meteoalarm-rssapi/archive/v1.0.5.zip
Project-URL: Bug Reports, https://github.com/xlcnd/meteoalarm-rssapi/issues
Project-URL: License, https://github.com/xlcnd/meteoalarm-rssapi/blob/dev/LICENSE.txt
Keywords: meteoalarm
Platform: any
Classifier: Programming Language :: Python
Classifier: Programming Language :: Python :: 3
Classifier: Programming Language :: Python :: 3.6
Classifier: Programming Language :: Python :: 3.7
Classifier: Programming Language :: Python :: 3.8
Classifier: Programming Language :: Python :: 3.9
Classifier: License :: OSI Approved :: GNU General Public License v3 (GPLv3)
Classifier: Operating System :: OS Independent
Classifier: Development Status :: 5 - Production/Stable
Classifier: Intended Audience :: Developers
Classifier: Topic :: Software Development :: Libraries :: Python Modules
